/* 
 * This file is part of MiniJVM (https://github.com/muhammad23012009/minijvm)
 * Copyright (c) 2025 Muhammad  <thevancedgamer@mentallysanemainliners.org>
 * 
 * This program is free software: you can redistribute it and/or modify  
 * it under the terms of the GNU General Public License as published by  
 * the Free Software Foundation, version 3.
 *
 * This program is distributed in the hope that it will be useful, but 
 * WITHOUT ANY WARRANTY; without even the implied warranty of 
 * MERCHANTABILITY or FITNESS FOR A PARTICULAR PURPOSE. See the GNU 
 * General Public License for more details.
 *
 * You should have received a copy of the GNU General Public License 
 * along with this program. If not, see <http://www.gnu.org/licenses/>.
 */

#include "builtins/builtins.h"
#include "array.h"
#include "method.h"
#include "object.h"

/* TODO: 
 * Implement exceptions
 * Implement proper garbage collection
 * Implement overloaded methods for superclasses
 * Free up objects created in a method when it returns
 * Improve built-in APIs/classes
 * Implement a proper types system
 * Figure out how to represent stored constants, do we represent them as objects or something else?
 * Does Java have a stack/heap system for variables?
 * ...etc
 */

#define DISPATCH() \
    ++frame->pc; \
    op = data[frame->pc]; \
    goto *opcodes[op]

Frame *frame_new(int max_stack, int max_local)
{
    Frame *frame = malloc(sizeof(Frame));
    frame->max_stack = max_stack;
    frame->max_locals = max_local;

    frame->stack = stack_new(max_stack);
    frame->locals = calloc(max_local, sizeof(Variant));

    return frame;
}

void frame_free(Frame *frame)
{
    stack_free(frame->stack);
    free(frame->locals);
    free(frame);
}

Method *get_method(ConstantPool *pool, Class *class, uint16_t index)
{
    Method *class_method;

    uint16_t name_and_type_index = pool->pool[index].method_ref.name_and_type_index;
    uint16_t method_index = pool->pool[name_and_type_index].name_and_type_info.name_index;
    uint16_t descriptor_index = pool->pool[name_and_type_index].name_and_type_info.descriptor_index;
    char *method_name = constant_pool_resolve_string(pool, method_index);
    char *descriptor = constant_pool_resolve_string(pool, descriptor_index);

    class_method = class_get_method(class, method_name, descriptor);

    return class_method;
}

void method_execute(Method *method, Frame *frame)
{
    printf("Beginning execution of method %s\n", method->name);
    /* Access code of method */
    uint8_t *data = method->data;
    ConstantPool *pool = method->class->pool;
    uint8_t op;

    static void *opcodes[] = {
        [2 ... 8] = &&iconst_x,
        [16] = &&bipush,
        [17] = &&sipush,
        [18] = &&ldc,
        [21] = &&iload,
        [25] = &&aload,
        [26 ... 29] = &&iload_x,
        [42 ... 45] = &&aload_x,
        [50] = &&aaload,
        [54] = &&istore,
        [58] = &&astore,
        [59 ... 62] = &&istore_x,
        [75 ... 78] = &&astore_x,
        [83] = &&aastore,
        [87] = &&pop,
        [89] = &&dup,
        [96] = &&iadd,
        [132] = &&iinc,
        [159 ... 164] = &&if_cmpx,
        [167] = &&j_goto,
        [172] = &&ireturn,
        [177] = &&j_return,
        [178] = &&getstatic,
        [179] = &&putstatic,
        [180] = &&getfield,
        [181] = &&putfield,
        [182] = &&invokevirtual,
        [183] = &&invokespecial,
        [186] = &&invokedynamic,
        [187] = &&new,
        [189] = &&anewarray,
        [190] = &&arraylength,
    };

    frame->pc = 0;
    frame->code = data;

    op = data[frame->pc];
    goto *opcodes[op];

    iconst_x: {
        int8_t const_int = op - 3;
        stack_push_int(frame->stack, const_int);
        DISPATCH();
    }

    bipush: {
        uint8_t byte = data[++frame->pc];
        stack_push_int(frame->stack, byte);
        DISPATCH();
    }

    sipush:
        uint16_t shrt = (data[++frame->pc] << 8) | data[++frame->pc];
        stack_push_int(frame->stack, shrt);
        DISPATCH();

    ldc: {
        uint8_t index = data[++frame->pc];
        uint8_t tag = constant_pool_get_tag(pool, index);
        Variant variant;

        switch (tag) {
            case CONSTANT_INT: {
                variant.data.int_val = constant_pool_resolve_int(pool, index);
                variant.type = VARIANT_TYPE_INT;
                break;
            }

            case CONSTANT_STRING: {
                Object *str_obj = object_new(classes_get_class(method->class->classes, "java/lang/String"));
                object_get_field(str_obj, "value")->value.data.ref = constant_pool_resolve_string(pool, index);
                variant.data.object = str_obj;
                variant.type = VARIANT_TYPE_OBJECT;
                break;
            }

            case CONSTANT_UTF8: {
                variant.data.ref = constant_pool_resolve_string(pool, index);
                variant.type = VARIANT_TYPE_REF;
                break;
            }
        }

        stack_push(frame->stack, variant);
        DISPATCH();
    }

    iload: {
        uint8_t index = data[++frame->pc];
        stack_push(frame->stack, frame->locals[index]);
        DISPATCH();
    }

    aload: {
        uint8_t index = data[++frame->pc];
        stack_push(frame->stack, frame->locals[index]);
        DISPATCH();
    }

    iload_x: {
        uint8_t local_index = op - 26;
        Variant item = frame->locals[local_index];
        stack_push(frame->stack, item);
        DISPATCH();
    }

    aload_x: {
        uint8_t local_index = op - 42;
        stack_push(frame->stack, frame->locals[local_index]);
        DISPATCH();
    }

    aaload: {
        int index = stack_pop(frame->stack).data.int_val;
        Array *array = stack_pop(frame->stack).data.ref;

        stack_push(frame->stack, array->value[index]);
        DISPATCH();
    }

    istore: {
        uint8_t local_index = data[++frame->pc];
        frame->locals[local_index] = stack_pop(frame->stack);
        DISPATCH();
    }

    astore: {
        uint8_t local_index = data[++frame->pc];
        frame->locals[local_index] = stack_pop(frame->stack);
        DISPATCH();
    }

    istore_x: {
        uint8_t local_index = op - 59;
        frame->locals[local_index] = stack_pop(frame->stack);
        DISPATCH();
    }

    astore_x: {
        uint8_t local_index = op - 75;
        frame->locals[local_index] = stack_pop(frame->stack);
        DISPATCH();
    }

    aastore: {
        Variant value = stack_pop(frame->stack);
        int index = stack_pop(frame->stack).data.int_val;
        Array *array = stack_pop(frame->stack).data.ref;

        array_set_value(array, index, value);
        DISPATCH();
    }

    pop:
        stack_pop(frame->stack);
        DISPATCH();

    dup:
        stack_dup(frame->stack);
        DISPATCH();

    iadd:
        int a1 = stack_pop(frame->stack).data.int_val;
        int a2 = stack_pop(frame->stack).data.int_val;
        stack_push_int(frame->stack, a1 + a2);
        DISPATCH();

    iinc:
        uint8_t index = data[++frame->pc];
        int8_t const_val = data[++frame->pc];
        frame->locals[index].data.int_val += const_val;
        DISPATCH();

    if_cmpx: {
        uint8_t cond = op - 159;
        int16_t branch_offset = (data[++frame->pc] << 8) | data[++frame->pc];
        int value2 = stack_pop(frame->stack).data.int_val;
        int value1 = stack_pop(frame->stack).data.int_val;

        static void *conditions[] = {
            &&do_eq, &&do_ne, &&do_lt, &&do_ge, &&do_gt, &&do_le,
        };

        goto *conditions[cond];

        do_eq:
            if (value1 == value2) goto branch;
            DISPATCH();

        do_ne:
            if (value1 != value2) goto branch;
            DISPATCH();

        do_lt:
            if (value1 < value2) goto branch;
            DISPATCH();

        do_ge:
            if (value1 >= value2) goto branch;
            DISPATCH();

        do_gt:
            if (value1 > value2) goto branch;
            DISPATCH();

        do_le:
            if (value1 <= value2) goto branch;
            DISPATCH();

        branch:
            frame->pc += branch_offset - 3;
            DISPATCH();
    }

    j_goto: {
        int16_t branch_offset = (data[++frame->pc] << 8) | data[++frame->pc];
        /* Two bytes for the branch offset, and one byte for DISPATCH */
        frame->pc += branch_offset - 3;
        DISPATCH();
    }

    ireturn:
        return;

    j_return:
        return;

    getstatic: {
        uint16_t index = (data[++frame->pc] << 8) | data[++frame->pc];
        Class *class = classes_get_class_from_index(method->class->classes, pool, index);
        if (class->static_field_count && !class->static_initialized) {
            class_initialize_static(class);
        }

        char *field_name = constant_pool_resolve_field_name(pool, index);
        Field *field = class_get_static_field(class, field_name);

        stack_push(frame->stack, field->value);
        DISPATCH();
    }

    putstatic: {
        uint16_t index = (data[++frame->pc] << 8) | data[++frame->pc];
        Class *class = classes_get_class_from_index(method->class->classes, pool, index);
        /* Check if the class has been initialized yet. */
        if (class->static_field_count && !class->static_initialized) {
            class_initialize_static(class);
        }

        Field *field = class_get_static_field(class, constant_pool_resolve_field_name(class->pool, index));

        /* TODO: Implement value conversion */
        field->value = stack_pop(frame->stack);
        DISPATCH();
    }

    getfield: {
        uint16_t index = (data[++frame->pc] << 8) | data[++frame->pc];
        Object *object = stack_pop(frame->stack).data.object;
        char *field_name = constant_pool_resolve_field_name(object->class->pool, index);
        Field *field = object_get_field(object, field_name);

        stack_push(frame->stack, field->value);
        DISPATCH();
    }

    putfield: {
        uint16_t index = (data[++frame->pc] << 8) | data[++frame->pc];
        Variant value = stack_pop(frame->stack);
        Object *object = stack_pop(frame->stack).data.object;

        char *field_name = constant_pool_resolve_field_name(object->class->pool, index);
        Field *field = object_get_field(object, field_name);

        field->value = value;
        DISPATCH();
    }

    invokevirtual: {
        uint16_t index = (data[++frame->pc] << 8) | data[++frame->pc];
        Class *class = classes_get_class_from_index(method->class->classes, pool, index);
        Method *class_method = get_method(pool, class, index);

        Frame *subframe = frame_new(class_method->max_stack, class_method->max_local);
        //printf("made new subframe for submethod %s in class %s with max stack %d virt\n", class_method->name, class->name, class_method->max_stack);

        int arguments_count = class_method->descriptors->arguments_count;

        for (int i = 1; i <= arguments_count; i++) {
            Variant item = stack_pop(frame->stack);
            subframe->locals[i] = item;
        }
        Variant item = stack_pop(frame->stack);
        subframe->locals[0] = item;

        if (class->built_in) {
            class_method->method(method, subframe);
        } else {
            method_execute(class_method, subframe);
        }

        //printf("finished execution of submethod %s\n", class_method->name);
        /* TODO: Instead of doing this, pass the frame of the invoker 
         * into the method being executed, and then push the result into
         * the invoker frame on return.
         */
        /* Take the returned value from the method, if it had one */
        if (class_method->descriptors &&
            class_method->descriptors->return_descriptor.type != DESCRIPTOR_VOID) {
            Variant item = stack_pop(subframe->stack);
            stack_push(frame->stack, item);
        }

        frame_free(subframe);
        DISPATCH();
    }

    invokespecial: {
        /* TODO: https://docs.oracle.com/javase/specs/jvms/se14/html/jvms-6.html#jvms-6.5.invokespecial 
         * Implement all of this
         */

        uint16_t index = (data[++frame->pc] << 8) | data[++frame->pc];
        Class *class = classes_get_class_from_index(method->class->classes, pool, index);
        Method *class_method = get_method(pool, class, index);

        Frame *subframe = frame_new(class_method->max_stack, class_method->max_local);
        //printf("made new subframe with max stack %d\n", class_method->max_stack);

        int arguments_count = class_method->descriptors->arguments_count;

        for (int i = 1; i <= arguments_count; i++) {
            Variant item = stack_pop(frame->stack);
            subframe->locals[i] = item;
        }

        Variant item = stack_pop(frame->stack);
        subframe->locals[0] = item;

        if (class->built_in) {
            class->pool = pool;
            class_method->method(class_method, subframe);
        } else {
            method_execute(class_method, subframe);
        }

        /* Take the returned value from the method, if it had one */
        if (class_method->descriptors &&
            class_method->descriptors->return_descriptor.type != DESCRIPTOR_VOID) {
            Variant item = stack_pop(subframe->stack);
            printf("got return\n");
            stack_push(frame->stack, item);
        }

        frame_free(subframe);
        DISPATCH();
    }

    invokedynamic: {
        DISPATCH();
    }

    new: {
        uint16_t index = (data[++frame->pc] << 8) | data[++frame->pc];
        Class *class = classes_get_class_from_index(method->class->classes, pool, index);
        Object *object = object_new(class);
        stack_push_object(frame->stack, object);
        DISPATCH();
    }

    anewarray: {
        uint16_t index = (data[++frame->pc] << 8) | data[++frame->pc];
        Class *class = classes_get_class_from_index(method->class->classes, pool, index);
        printf("Creating new array of class %s\n", class->name);

        int count = stack_pop(frame->stack).data.int_val;
        Array *array = array_new(class, count);
        stack_push_ref(frame->stack, array);

        DISPATCH();
    }

    arraylength: {
        Array *array = stack_pop(frame->stack).data.ref;
        stack_push_int(frame->stack, array->count);

        DISPATCH();
    }
}

/* Field creation/accession methods */
FieldInfo fields_get_field(Fields *fields, char *name)
{
    for (int i = 0; i < fields->count; i++) {
        FieldInfo info = fields->fields[i];
        if (!strcmp(info.name.name, name))
            return info;
    }
}

Fields *fields_new(Reader *reader, ConstantPool *pool)
{
    Fields *fields = malloc(sizeof(Fields));
    fields->count = reader_read_uint16_be(reader);
    if (fields->count <= 0) {
        free(fields);
        return NULL;
    }

    fields->fields = malloc(sizeof(FieldInfo) * fields->count);

    for (int i = 0; i < fields->count; i++) {
        FieldInfo *field = &fields->fields[i];
        field->access_flags = reader_read_uint16_be(reader);
        field->name.index = reader_read_uint16_be(reader);
        field->name.name = constant_pool_resolve_string(pool, field->name.index);
        field->descriptor.index = reader_read_uint16_be(reader);
        field->descriptor.descriptor = constant_pool_resolve_string(pool, field->descriptor.index);
        field->attributes = attributes_new(reader, pool);
    }

    return fields;
}

void fields_free(Fields *fields)
{
    if (!fields)
        return;

    for (int i = 0; i < fields->count; i++) {
        FieldInfo info = fields->fields[i];
        attributes_free(info.attributes);
    }
    free(fields->fields);
    free(fields);
}

/* Class/methods code */
Class *class_parse_file(Classes *classes, char *filename)
{
    Class *class = malloc(sizeof(Class));
    Method *static_init = NULL;
    struct stat filestat;
    FILE *file;
    memset(class, 0, sizeof(Class));

    int status = stat(filename, &filestat);
    if (status < 0) {
        printf("File not found!\n");
        free(class);
        return NULL;
    }

    file = fopen(filename, "r");
    class->data = malloc(filestat.st_size);
    fread(class->data, filestat.st_size, 1, file);
    fclose(file);

    class->built_in = false;
    Reader *reader = class->reader = reader_new(class->data, filestat.st_size);

    printf("class processing started!\n");

    /* Start parsing the classfile */
    uint32_t magic = reader_read_uint32_be(reader);
    if (magic != 0xCAFEBABE) {
        printf("Invalid class!\n");
        return NULL;
        /* TODO: Cleanup... */
    }

    uint16_t minor_version = reader_read_uint16_be(reader);
    uint16_t major_version = reader_read_uint16_be(reader);

    class->pool = constant_pool_new(reader);
    class->flags = reader_read_uint16_be(reader);
    class->name = constant_pool_resolve_string(class->pool, reader_read_uint16_be(reader));
    /* TODO: Handle parents later */
    class->parent = classes_get_class(classes, constant_pool_resolve_string(class->pool, reader_read_uint16_be(reader)));

    printf("some basic information...\n");

    uint16_t interfaces_count = reader_read_uint16_be(reader);
    Interface *interfaces = malloc(sizeof(Interface) * interfaces_count);

    for (int i = 0; i < interfaces_count; i++) {
        Interface *iface = &interfaces[i];
        iface->index = reader_read_uint16_be(reader);
        iface->interface = constant_pool_resolve_string(class->pool, iface->index);
    }

    /* TODO: Eventually drop these somehow */
    class->class_fields = fields_new(reader, class->pool);
    class->method_fields = fields_new(reader, class->pool);
    class->attributes = attributes_new(reader, class->pool);
    class->static_field_count = 0;
    class->static_initialized = false;

    if (class->class_fields) {
        /* Parse static fields within the class and separate them */
        for (int i = 0; i < class->class_fields->count; i++) {
            FieldInfo info = class->class_fields->fields[i];
            /* ACC_STATIC */
            if (info.access_flags & 0x0008) {
                class->static_field_count++;
            }
        }

        if (class->static_field_count) {
            class->static_fields = malloc(sizeof(Field) * class->static_field_count);
            int j = 0;
            for (int i = 0; i < class->class_fields->count; i++) {
                FieldInfo info = class->class_fields->fields[i];
                if (info.access_flags & 0x0008) {
                    Field *field = &class->static_fields[j++];
                    field->name = info.name.name;
                    field->class = class;
                }
            }
        }
    }

    for (int i = 0; i < class->method_fields->count; i++) {
        FieldInfo info = class->method_fields->fields[i];
        class_add_method(class, info);
    }

    printf("fields and methods...\n");

    if (!constant_pool_resolve_unknowns(class->pool, classes, class)) {
        class_free(class);
        return NULL;
    }

    printf("...and done!\n");
    return class;
}

void class_initialize_static(Class *class)
{
    Method *static_init = NULL;

    if (class->static_field_count && (static_init = class_get_method(class, "<clinit>", "()V"))) {
        class->static_initialized = true;
        Frame *frame = frame_new(static_init->max_stack, static_init->max_local);

        if (class->built_in)
            static_init->method(static_init, frame);
        else
            method_execute(static_init, frame);

        frame_free(frame);
    }
}

void class_free(Class *class)
{
    if (!class->built_in) {
        attributes_free(class->attributes);
        fields_free(class->class_fields);
        fields_free(class->method_fields);
        constant_pool_free(class->pool);
        free(class->reader);
        free(class->data);
    }

    for (int j = 0; j < class->methods_count; j++) {
        descriptors_free(class->methods[j]->descriptors);
        free(class->methods[j]);
    }

    free(class->methods);
}

/* Built-in classes will have no constant pools or any other associated
 * properties set. They will only contains a name and methods.
*/
Class *class_create_builtin(char *name, builtins *class_builtins, Classes *classes)
{
    Class *class = malloc(sizeof(Class));
    memset(class, 0, sizeof(Class));
    class->built_in = true;
    class->name = name;

    if (class_builtins->parent)
        class->parent = classes_get_class(classes, class_builtins->parent);

    class->methods_count = class_builtins->methods_length;
    class->methods = malloc(sizeof(Method*) * class->methods_count);

    for (int i = 0; i < class_builtins->methods_length; i++) {
        builtin_methods bmethod = class_builtins->methods[i];
        Method *method = class->methods[i] = malloc(sizeof(Method));
        method->name = bmethod.name;
        method->class = class;
        method->method = bmethod.method;
        method->flags = 0; // TODO: Implement method flags

        if (strcmp(bmethod.descriptor, "") != 0) {
            /* This built-in method has predefined arguments and returns */
            method->descriptors = descriptors_new(bmethod.descriptor);
            method->max_local = method->descriptors->arguments_count + 1; // +1 for `this`
            method->max_stack = bmethod.max_stack;
        }
    }

    for (int i = 0; i < class_builtins->fields_length; i++) {
        builtin_fields *field = &class_builtins->fields[i];
        if (field->flags & 0x0008) { // ACC_STATIC
            class->static_field_count++;
        } else {
            class->class_fields = malloc(sizeof(Fields));
            class->class_fields->count = class_builtins->fields_length;
            class->class_fields->fields = malloc(sizeof(Field) * class->class_fields->count);

            for (int j = 0; j < class_builtins->fields_length; j++) {
                builtin_fields *bf = &class_builtins->fields[j];
                FieldInfo *fi = &class->class_fields->fields[j];
                fi->name.name = bf->name;
                fi->descriptor.descriptor = NULL; // TODO: Implement built-in field descriptors
                fi->access_flags = bf->flags;
            }
        }
    }

    if (class->static_field_count) {
        class->static_fields = malloc(sizeof(Field) * class->static_field_count);
        int j = 0;
        for (int i = 0; i < class_builtins->fields_length; i++) {
            builtin_fields *field = &class_builtins->fields[i];
            if (field->flags & 0x0008) { // ACC_STATIC
                Field *f = &class->static_fields[j++];
                f->name = field->name;
                f->class = class;
            }
        }
    }

    return class;
}

void class_add_method(Class *class, FieldInfo method_info)
{
    Method *method = malloc(sizeof(Method));
    AttributeInfo code = attributes_get_attribute(method_info.attributes, "Code");

    method->name = method_info.name.name;
    method->class = class;
    method->data_length = code.CodeAttribute.code_length;
    method->data = code.CodeAttribute.code;
    method->flags = method_info.access_flags;
    method->max_stack = code.CodeAttribute.max_stack;
    method->max_local = code.CodeAttribute.max_locals;
    method->descriptors = descriptors_new(method_info.descriptor.descriptor);

    if (class->methods)
        class->methods = realloc(class->methods, (sizeof(Method*) * (class->methods_count + 1)));
    else
        class->methods = malloc(sizeof(Method*));

    class->methods[class->methods_count] = method;
    class->methods_count++;
}

Method *class_get_method(Class *class, char *name, char *descriptor)
{
    for (int i = 0; i < class->methods_count; i++) {
        Method *method = class->methods[i];
        if (!strcmp(method->name, name) && !strcmp(method->descriptors->descriptor, descriptor))
            return method;
    }

    return NULL;
}

Field *class_get_static_field(Class *class, char *name)
{
    for (int i = 0; i < class->static_field_count; i++) {
        Field *f = &class->static_fields[i];
        if (!strcmp(name, f->name))
            return f;
    }

    return NULL;
}

/* Gets class method from index. Index is expected to be of type `method_ref` */
Method *class_get_method_from_index(Class *class, uint16_t index)
{
    uint16_t method_index = class->pool->pool[index].method_ref.name_and_type_index;
    uint16_t name_index = class->pool->pool[method_index].name_and_type_info.name_index;
    uint16_t descriptor_index = class->pool->pool[method_index].name_and_type_info.descriptor_index;

    char *name = constant_pool_resolve_string(class->pool, name_index);
    char *descriptor = constant_pool_resolve_string(class->pool, descriptor_index);
    return class_get_method(class, name, descriptor);
}

bool classes_add_class(Classes *classes, Class *class)
{
    if (!classes || !class)
        return false;

    class->classes = classes;
    classes->classes = realloc(classes->classes, (sizeof(Class*) * (classes->count + 1)));
    classes->classes[classes->count++] = class;

    return true;
}

Class *classes_get_class(Classes *classes, char *name)
{
    for (int i = 0; i < classes->count; i++) {
        Class *class = classes->classes[i];
        if (!strcmp(class->name, name))
            return class;
    }

    return NULL;
}

/* TODO: Fix this method */
Class *classes_get_class_from_index(Classes *classes, ConstantPool *pool, uint16_t index)
{
    char *name = constant_pool_resolve_class_name(pool, index);
    return classes_get_class(classes, name);
}

Method *classes_get_main_method(Classes *classes)
{
    for (int i = 0; i < classes->count; i++) {
        Class *class = classes->classes[i];
        for (int j = 0; j < class->methods_count; j++) {
            Method *method = class->methods[j];
            if (!strcmp(method->name, "main")) {
                // We found the main method. Great. Mark this as our main class.
                printf("Found method main in class %s\n", class->name);
                classes->main_class = class;
                return class->methods[j];
            }
        }
    }

    return NULL;
}

Classes *classes_new()
{
    Classes *classes = malloc(sizeof(Classes));
    classes->count = 0;
    classes->classes = NULL;

    return classes;
}

void classes_free(Classes *classes)
{
    for (int i = 0; i < classes->count; i++) {
        Class *class = classes->classes[i];
        class_free(class);
    }
    free(classes->classes);
    free(classes);
}
